deepdish/__init__.py
deepdish/conf.py
deepdish/core.py
deepdish/image.py
deepdish/six.py
deepdish/io/__init__.py
deepdish/io/hdf5io.py
deepdish/io/ls.py
deepdish/parallel/__init__.py
deepdish/parallel/fallback.py
deepdish/parallel/mpi.py
deepdish/util/__init__.py
deepdish/util/padding.py
deepdish/util/saveable.py
deepdish/util/zca_whitening.py
deepdish-0.3.7.data/scripts/ddls
deepdish-0.3.7.dist-info/LICENSE
deepdish-0.3.7.dist-info/METADATA
deepdish-0.3.7.dist-info/WHEEL
deepdish-0.3.7.dist-info/top_level.txt
deepdish-0.3.7.dist-info/RECORD
